{
	"type": "GStreamer",
	"template": ["uridecodebin name=source",
		" ! gvadetect model={models[object_detection][person_vehicle_bike][network]} name=detection",
				" ! gvametaconvert name=metaconvert",
				" ! gvapython name=edgexbridge module=/home/video-analytics-serving/samples/edgex_bridge/extensions/edgex_transform.py class=Bridge",
				" ! gvametapublish name=destination",
				" ! gvawatermark ! videoconvert ! fpsdisplaysink video-sink=ximagesink"
			],
	"description": "Person Vehicle Bike Detection based on person-vehicle-bike-detection-crossroad-0078, with events emitted to EdgeX.",
	"parameters": {
		"type": "object",
		"properties": {
			"edgexbridge": {
				"element": { "name":"edgexbridge",
					"property":"kwarg",
					"format":"json"
				},
				"type": "object"},
				"properties": {
				"topic": {
					"element": "edgexbridge",
					"type": "string",
					"default": "edgex"
				},
				"mqtt_devicename": {
					"element": "edgexbridge",
					"type": "string",
					"default": "objectDetect-mqtt"
				}
			},
			"detection-device": {
				"element": {
					"name": "detection",
					"property": "device"
				},
				"type": "string"
			},
			"detection-model-instance-id": {
				"element": {
					"name": "detection",
					"property": "model-instance-id"
				},
				"type": "string",
				"default": "person_vehicle_bike_detection"
			},
			"inference-interval": {
				"element": "detection",
				"type": "integer"
			},
			"threshold": {
				"element": "detection",
				"type": "number"
			}
		}
	}
}
